spiker-1.0.5.data/scripts/frag_count.py
spiker-1.0.5.data/scripts/run_deseq2.py
spiker-1.0.5.data/scripts/spiker.py
spiker-1.0.5.data/scripts/split_bam.py
spikers/PE.py
spikers/__init__.py
spikers/cal_FRiP.py
spikers/process_bam.py
spikers/run_bowtie2.py
spikers/run_macs2.py
spikers/write_bw.py
spiker-1.0.5.dist-info/LICENSE.txt
spiker-1.0.5.dist-info/METADATA
spiker-1.0.5.dist-info/WHEEL
spiker-1.0.5.dist-info/top_level.txt
spiker-1.0.5.dist-info/RECORD
