Metadata-Version: 2.1
Name: spiker
Version: 1.0.5
Summary: spiker (Analysis workflow for ChIP-seq data with spike-in)
Home-page: https://spiker.readthedocs.io/en/latest/index.html
Author: Liguo Wang
Author-email: wangliguo78@gmail.com
License: MIT License
Keywords: ChIP-seq,ChIPseq,spike-in,spikein,chromatin,peak calling
Platform: Linux
Platform: MacOS
Classifier: Development Status :: 5 - Production/Stable
Classifier: Environment :: Console
Classifier: Intended Audience :: Science/Research
Classifier: License :: OSI Approved :: GNU General Public License v2 (GPLv2)
Classifier: Operating System :: MacOS :: MacOS X
Classifier: Operating System :: POSIX
Classifier: Programming Language :: Python
Classifier: Topic :: Scientific/Engineering :: Bio-Informatics
Requires: cython (>=0.17)
Requires-Python: >=3.5
License-File: LICENSE.txt
Requires-Dist: numpy
Requires-Dist: scipy
Requires-Dist: pysam
Requires-Dist: deeptools
Requires-Dist: macs2
Requires-Dist: pyBigWig
